brica.cpython-37m-darwin.so
BriCA2-0.5.4.data/headers/assocvec.hpp
BriCA2-0.5.4.data/headers/brica.hpp
BriCA2-0.5.4.data/headers/buffer.hpp
BriCA2-0.5.4.data/headers/component.hpp
BriCA2-0.5.4.data/headers/functor.hpp
BriCA2-0.5.4.data/headers/mpi.hpp
BriCA2-0.5.4.data/headers/port.hpp
BriCA2-0.5.4.data/headers/scheduler.hpp
BriCA2-0.5.4.data/headers/thread_pool.hpp
_brica/__init__.py
BriCA2-0.5.4.dist-info/LICENSE
BriCA2-0.5.4.dist-info/METADATA
BriCA2-0.5.4.dist-info/WHEEL
BriCA2-0.5.4.dist-info/top_level.txt
BriCA2-0.5.4.dist-info/RECORD
